{
  "constituent": "marsh, water, water droplets, water pistol, summon, seduce, sword, dagger, mouth",
  "frameNoV4": "137",
  "frameNoV6": "145",
  "hanviet": "CHIỂU",
  "heisigComment": "",
  "heisigStory": "Unlike the meadow with its cliffs, the <b>marsh</b>lands are low and near a source of <i>water</i> that feeds them until they get soggy through and through. Why certain land becomes <b>marshy</b> is probably due to the fact that it felt thirsty, and so tried its best to <i>seduce</i> the <i>water</i> over to its side. But, like most inordinate <i>seductions</i>, the last state of the victim is worse than the first. Hence the slushy <b>marsh</b>.",
  "hint": "",
  "id": "145",
  "jlpt": "1",
  "jouYou": "JH",
  "kanji": "沼",
  "keyword": "marsh",
  "koohiiStory1": "The marshlands near Mordor seduce Frodo into gazing upon them, and he falls into the water--splash!",
  "koohiiStory2": "A marsh is where water is seduced into the ground.",
  "kunYomi": "ぬま",
  "lessonNo": "8",
  "myStory": "lầy lội. vùng trũng. sung sướng trong nước ",
  "onYomi": "ショウ",
  "readingExamples": "沼 (ぬま)",
  "strokeCount": "8",
  "strokeDiagram": "<img src=\"E6B2BC.png\" />",
  "words": "沼(ぬま): swamp, bog, pond, lake"
}