{
  "constituent": "tale, say, words, keitai, mouth, tongue, thousand, mouth, mouth2",
  "frameNoV4": "344",
  "frameNoV6": "368",
  "hanviet": "THOẠI",
  "heisigComment": "",
  "heisigStory": "That the <i>words</i> of the <i>tongue</i> should come to mean a <b>tale</b> is clear from the etymology: a <b><i>tale</i></b> is something \"talked,\" not something read from a book.",
  "hint": "",
  "id": "368",
  "jlpt": "5",
  "jouYou": "2",
  "kanji": "話",
  "keyword": "tale",
  "koohiiStory1": "Tales are always spoken, not written, and because of this, words fly out of your tongue, rather than your pen.",
  "koohiiStory2": "Tales are spoken words, passed on from person to person, eventually being spoken by a thousand mouths.",
  "kunYomi": "はな.す、はなし",
  "lessonNo": "15",
  "myStory": "câu truyện truyền thuyết. nói qua lưỡi là câu truyện truyền miệng",
  "onYomi": "ワ",
  "readingExamples": "話す (はな.す), 話 (はなし)",
  "strokeCount": "13",
  "strokeDiagram": "<img src=\"E8A9B1.png\" />",
  "words": "対話(たいわ): interactive, interaction, conversation, dialogue<br>話し合い(はなしあい): discussion, conference<br>受話器(じゅわき): telephone receiver<br>神話(しんわ): myth, legend<br>童話(どうわ): fairy-tale<br>話し合う(はなしあう): discuss, talk together<br>話し掛ける(はなしかける): accost a person, talk (to someone)<br>話中(はなしちゅう): while talking, the line is busy<br>話題(わだい): topic, subject<br>会話(かいわ): conversation<br>世話(せわ): take care of<br>電話(でんわ): telephone<br>話(はなし): talk, speech, chat, story, conversation<br>話す(はなす): speak"
}