{
  "constituent": "demand, rain, weather, comb",
  "frameNoV4": "1165",
  "frameNoV6": "1249",
  "heisigComment": "",
  "heisigStory": "The sense of <b>demand</b> is best captured by thinking of the economic principle of \"supply and <b>demand</b>.\" The primitives: <i>rain</i> . . . <i>comb</i>.",
  "hint": "",
  "id": "1249",
  "jlpt": "1",
  "jouYou": "JH",
  "kanji": "需",
  "keyword": "demand",
  "koohiiStory1": "Supply and demand is a simple concept: when it rains, the demand for combs goes up to deal with wet hair.",
  "koohiiStory2": "If it´s raining combs, then the demand for them sure does drop.",
  "kunYomi": "",
  "lessonNo": "31",
  "myStory": "",
  "onYomi": "ジュ",
  "readingExamples": "",
  "strokeCount": "14",
  "strokeDiagram": "<img src=\"E99C80.png\" />",
  "words": "需要(じゅよう): demand, request<br>必需品(ひつじゅひん): necessities, necessary article, requisite, essential"
}