{"constituent": "curtain, graveyard, flowers, sun, day, large, St. Bernard, towel", "hanviet": "M\u1ea0C, M\u1ed8, M\u00c1N", "kanji": "\u5e55", "keyword": "curtain", "kunYomi": "\u3068\u3070\u308a", "myStory": "m\u00e0n gi\u00f3. ko ph\u1ea3i l\u00e0 kh\u0103n m\u00e0 l\u00e0 m\u00e0n gi\u00f3. kh\u0103n kh\u0103n ph\u1ee5c v\u1ee5 ng\u00f4i nh\u00e0", "onYomi": "\u30de\u30af\u3001\u30d0\u30af", "readingExamples": "\u5e55\u5207\u308c (\u307e\u304f\u304e\u308c), \u5929\u5e55 (\u3066\u3093\u307e\u304f), \u6697\u5e55 (\u3042\u3093\u307e\u304f)", "strokeDiagram": "<img src=\"E5B995.png\" />", "words": "\u5e55(\u3068\u3070\u308a): curtain, bunting, act (in play)<br>\u5e55(\u307e\u304f): curtain, screen"}