{"constituent": "Mr, flag, strung together, salad, animal legs, eight, cruise missile, missile, wind, crotch", "hanviet": "\u0110I\u1ec6N, \u0110I\u1ebeN", "kanji": "\u6bbf", "keyword": "Mr.", "kunYomi": "\u3068\u306e\u3001-\u3069\u306e", "myStory": "", "onYomi": "\u30c7\u30f3\u3001\u30c6\u30f3", "readingExamples": "\u6bbf\u5802 (\u3067\u3093\u3069\u3046), \u5bae\u6bbf (\u304d\u3085\u3046\u3067\u3093), \u8cb4\u6bbf (\u304d\u3067\u3093), \u6bbf (\u3068\u306e), \u6bbf (\u3069\u306e)", "strokeDiagram": "<img src=\"E6AEBF.png\" />", "words": [["\u5bae\u6bbf", "\u304d\u3085\u3046\u3067\u3093", "palace"], ["\u6bbf", "\u3057\u3093\u304c\u308a", "rear, rear unit guard"], ["\u795e\u6bbf", "\u3057\u3093\u3067\u3093", "temple, sacred place"], ["\u6c88\u6bbf", "\u3061\u3093\u3067\u3093", "precipitation, settlement"], ["\u6bbf\u69d8", "\u3068\u306e\u3055\u307e", "feudal lord"]]}