{"constituent": "every, reclining, lying down, mother", "hanviet": "M\u1ed6I", "kanji": "\u6bce", "keyword": "every", "kunYomi": "\u3054\u3068\u3001-\u3054\u3068.\u306b", "myStory": "m\u1ed7i", "onYomi": "\u30de\u30a4", "readingExamples": "", "strokeDiagram": "<img src=\"E6AF8E.png\" />", "words": "\u6bce(\u3054\u3068): each respectively<br>\u6bce\u5ea6(\u307e\u3044\u3069): each time, common service-sector greeting<br>\u6bce\u671d(\u307e\u3044\u3042\u3055): every morning<br>\u6bce\u6708(\u307e\u3044\u3052\u3064): every month, each month, monthly<br>\u6bce\u9031(\u307e\u3044\u3057\u3085\u3046): every week<br>\u6bce\u65e5(\u307e\u3044\u306b\u3061): every day<br>\u6bce\u6669(\u307e\u3044\u3070\u3093): every night"}