{"constituent": "drown, water, water droplets, water pistol, cruise missile, missile, wind, crotch", "hanviet": "M\u1ed8T", "kanji": "\u6ca1", "keyword": "drown", "kunYomi": "\u304a\u307c.\u308c\u308b\u3001\u3057\u305a.\u3080\u3001\u306a\u3044", "myStory": "\u0111u\u1ed1i n\u01b0\u1edbc. ch\u00ecm. n\u01b0\u1edbc ph\u00f3ng nh\u01b0ng b\u1ecb \u0111u\u1ed1i", "onYomi": "\u30dc\u30c4\u3001\u30e2\u30c4", "readingExamples": "", "strokeDiagram": "<img src=\"E6B2A1.png\" />", "words": [["\u6c88\u6ca1", "\u3061\u3093\u307c\u3064", "sinking, foundering"], ["\u6ca1\u53ce", "\u307c\u3063\u3057\u3085\u3046", "forfeited"], ["\u6ca1\u843d", "\u307c\u3064\u3089\u304f", "ruin, fall, collapse"]]}