{"constituent": "true, ten, needle, eye, tool, one, animal legs, eight", "hanviet": "CH\u00c2N", "kanji": "\u771f", "keyword": "true", "kunYomi": "\u307e\u3001\u307e-\u3001\u307e\u3053\u3068", "myStory": "th\u1eadt s\u1ef1. m\u01b0\u1eddi c\u00f4ng c\u1ee5 d\u00f9ng \u0111\u1ec3 t\u00ecm s\u1ef1 th\u1eadt", "onYomi": "\u30b7\u30f3", "readingExamples": "\u771f (\u307e)", "strokeDiagram": "<img src=\"E79C9F.png\" />", "words": [["\u751f\u771f\u9762\u76ee", "\u304d\u307e\u3058\u3081", "too serious, person who is too serious, honesty, sincerity"], ["\u771f\u5b9f", "\u3055\u306a", "truth, reality"], ["\u771f\u73e0", "\u3057\u3093\u3058\u3085", "pearl"], ["\u771f\u76f8", "\u3057\u3093\u305d\u3046", "truth, real situation"], ["\u771f\u7406", "\u3057\u3093\u308a", "truth"], ["\u771f\u4e0a", "\u307e\u3046\u3048", "just above, right overhead"], ["\u771f\u5fc3", "\u307e\u3053\u3053\u308d", "sincerity, devotion"], ["\u771f\u306b", "\u307e\u3053\u3068\u306b", "truly, actually, really"], ["\u771f\u4e0b", "\u307e\u3057\u305f", "right under, directly below"], ["\u771f\u3063\u4e8c\u3064", "\u307e\u3063\u3077\u305f\u3064", "in two equal parts"], ["\u771f\u3093\u524d", "\u307e\u3093\u307e\u3048", "right in front, under the nose"], ["\u771f\u3093\u4e38\u3044", "\u307e\u3093\u307e\u308b\u3044", "perfectly circular"], ["\u771f\u7a7a", "\u3057\u3093\u304f\u3046", "vacuum, hollow, empty"], ["\u771f\u5263", "\u3057\u3093\u3051\u3093", "seriousness, earnestness"], ["\u771f\u9762\u76ee", "\u307e\u3058\u3081", "diligent, serious, honest"], ["\u771f\u3063\u8d64", "\u307e\u3063\u304b", "deep red, flushed (of face)"], ["\u771f\u3063\u6697", "\u307e\u3063\u304f\u3089", "total darkness, pitch dark, shortsightedness"], ["\u771f\u3063\u9ed2", "\u307e\u3063\u304f\u308d", "pitch black"], ["\u771f\u3063\u9752", "\u307e\u3063\u3055\u304a", "deep blue, ghastly pale"], ["\u771f\u3063\u5148", "\u307e\u3063\u3055\u304d", "the head, the foremost, beginning"], ["\u771f\u3063\u767d", "\u307e\u3063\u3057\u308d", "pure white"], ["\u771f\u3063\u76f4\u3050", "\u307e\u3063\u3059\u3050", "straight (ahead), direct, upright, erect, honest, frank"], ["\u771f\u4f3c", "\u307e\u306d", "mimicry, imitation, behavior, pretense"], ["\u771f\u4f3c\u308b", "\u307e\u306d\u308b", "mimic, imitate"], ["\u771f\u3093\u4e2d", "\u307e\u3093\u306a\u304b", "middle, center, half way"], ["\u5199\u771f", "\u3057\u3083\u3057\u3093", "photograph"]]}