{"constituent": "rebuke, say, words, keitai, mouth, meeting of butchers, moon, month, flesh, part of the body, sword, sabre, saber", "hanviet": "D\u1ee4", "kanji": "\u8aed", "keyword": "rebuke", "kunYomi": "\u3055\u3068.\u3059", "myStory": "nh\u1eafc nh\u1edf. thuy\u1ebft ph\u1ee5c. nh\u1eefng l\u1eddi n\u00f3i b\u1ecb \u0103n tr\u1ed9m n\u00ean nh\u1eafc nh\u1edf", "onYomi": "\u30e6", "readingExamples": "\u8aed\u3059 (\u3055\u3068.\u3059)", "strokeDiagram": "<img src=\"E8ABAD.png\" />", "words": ""}