{"constituent": "play, banner, direction, compass, direction, reclining, lying down, child, road", "hanviet": "DU", "kanji": "\u904a", "keyword": "play", "kunYomi": "\u3042\u305d.\u3076\u3001\u3042\u305d.\u3070\u3059", "myStory": "", "onYomi": "\u30e6\u30a6\u3001\u30e6", "readingExamples": "\u904a\u622f (\u3086\u3046\u304e), \u904a\u96e2 (\u3086\u3046\u308a), \u4ea4\u904a (\u3053\u3046\u3086\u3046), \u904a\u3076 (\u3042\u305d.\u3076)", "strokeDiagram": "<img src=\"E9818A.png\" />", "words": "\u904a\u7267(\u3086\u3046\u307c\u304f): nomadism<br>\u904a\u5712\u5730(\u3086\u3046\u3048\u3093\u3061): amusement park<br>\u904a\u3073(\u3042\u305d\u3073): play<br>\u904a\u3076(\u3042\u305d\u3076): play, make a visit (esp. for pleasure), be idle, do nothing"}