{
  "data": [
    {
      "_id": "3f622868b00cf393d2dd93ed952946b2",
      "means": [
        {
          "examples": null,
          "kind": null,
          "mean": "10 ^ 28; một nghìn lũy thừa 9 x 10 (Mỹ); một triệu lũy thừa 8 x 10000 (Anh)"
        }
      ],
      "mobileId": 57413,
      "phonetic": "",
      "word": "壌"
    },
    {
      "_id": "993ac06591dc13e564a87d6ef9d2d46d",
      "means": [
        {
          "examples": null,
          "kind": "n",
          "mean": "earth, yellow soil, yellow ochre (ocher), loess"
        },
        {
          "examples": null,
          "kind": null,
          "mean": "Hades, hell, underworld, world of the dead"
        }
      ],
      "mobileId": 279506,
      "phonetic": "こうじょう",
      "word": "黄壌"
    },
    {
      "_id": "c1501ee68b95a76792cb85cf0dbdec2d",
      "means": [
        {
          "examples": null,
          "kind": "n",
          "mean": "thiên đàng và trái đất"
        }
      ],
      "mobileId": 151772,
      "phonetic": "",
      "word": "霄壌"
    },
    {
      "_id": "f14fb31d12c81e03ec4c7c97a9cb599b",
      "means": [
        {
          "examples": null,
          "kind": "n",
          "mean": "to stamp on the ground rhythmically while singing"
        },
        {
          "examples": null,
          "kind": null,
          "mean": "ancient Chinese game of wooden clog throwing"
        }
      ],
      "mobileId": 262785,
      "phonetic": "げきじょう",
      "word": "撃壌"
    },
    {
      "_id": "45cb52b868cdf707f15bbf08c0e10e02",
      "means": [
        {
          "examples": null,
          "kind": "n, vs",
          "mean": "(people) sing the praises (enjoy the blessings) of peace"
        }
      ],
      "mobileId": 214119,
      "phonetic": "こふくげきじょう",
      "word": "鼓腹撃壌"
    }
  ],
  "found": true,
  "status": 200
}