{
  "data": [
    {
      "_id": "35e94b76fb726c8818e40de107604199",
      "means": [
        {
          "examples": null,
          "kind": null,
          "mean": "vợ"
        },
        {
          "examples": null,
          "kind": "n",
          "mean": "vợ (tôi) ."
        }
      ],
      "mobileId": 53463,
      "opposite_word": [
        "夫"
      ],
      "phonetic": "つま",
      "related_words": {
        "word": [
          "稲妻",
          "人妻",
          "夫妻",
          "新妻",
          "愛妻",
          "妻子",
          "一夫多妻"
        ]
      },
      "synsets": [
        {
          "base_form": "妻",
          "entry": [
            {
              "definition_id": "",
              "synonym": [
                "夫人",
                "細君",
                "嫁",
                "女性",
                "家内",
                "裏方",
                "ミセス",
                "女",
                "婦人",
                "令室",
                "令夫人",
                "奥様",
                "刀自",
                "室",
                "御上",
                "令閨",
                "愚妻",
                "人妻",
                "女房",
                "上様"
              ]
            }
          ],
          "pos": "noun"
        }
      ],
      "word": "妻"
    },
    {
      "_id": "18dd57e50094ff765ae2fa2a3a9db860",
      "means": [
        {
          "examples": null,
          "kind": "n",
          "mean": "ex-wife, former wife"
        }
      ],
      "mobileId": 228443,
      "phonetic": "もとつま",
      "word": "元妻"
    },
    {
      "_id": "18dd57e50094ff765ae2fa2a3acc2c90",
      "means": [
        {
          "examples": null,
          "kind": "n",
          "mean": "wife who lives elsewhere but regularly visits her husband"
        }
      ],
      "mobileId": 229949,
      "phonetic": "かよいづま",
      "word": "通い妻"
    },
    {
      "_id": "0a951fdb8a16236250ffda52cd7f4413",
      "means": [
        {
          "examples": null,
          "kind": "n",
          "mean": "to prostitute oneself làm đĩ, mãi dâm, bán rẻ (danh dự, tên tuổi, tài năng...)"
        }
      ],
      "mobileId": 13830,
      "phonetic": "ひとよづま",
      "related_words": {
        "word": [
          "夜",
          "一",
          "妻",
          "一夜"
        ]
      },
      "synsets": [
        {
          "base_form": "一夜妻",
          "entry": [
            {
              "definition_id": "",
              "synonym": [
                "傀儡",
                "遊女",
                "淫婦",
                "売春婦",
                "傾城",
                "売女",
                "倡婦",
                "傾国",
                "売笑婦",
                "娼妓",
                "女郎",
                "娼婦",
                "淫売"
              ]
            }
          ],
          "pos": "noun"
        }
      ],
      "word": "一夜妻"
    },
    {
      "_id": "2aaa6af3b9fed0a5847abe38c0114e9d",
      "means": [
        {
          "examples": null,
          "kind": "v1, vt",
          "mean": "to marry off, to espouse to"
        }
      ],
      "mobileId": 189698,
      "phonetic": "めあわせる",
      "word": "妻合わせる"
    },
    {
      "_id": "0e0c844d73b2e7de16d7fca193f80a64",
      "means": [
        {
          "examples": null,
          "kind": "n",
          "mean": "cựu vợ"
        }
      ],
      "mobileId": 25785,
      "phonetic": "きゅうつま",
      "related_words": {
        "word": [
          "妻"
        ]
      },
      "word": "旧妻"
    },
    {
      "_id": "54053bd79d053f61f90b2e3ada31787a",
      "means": [
        {
          "examples": [
            {
              "content": "切り妻壁",
              "mean": "vách hiên",
              "transcription": "きりつまかべ"
            },
            {
              "content": "切り妻屋根",
              "mean": "gác mái hiên .",
              "transcription": "きりつまやね"
            }
          ],
          "kind": "n",
          "mean": "đầu hồi; mái che; mái hiên"
        }
      ],
      "mobileId": 77778,
      "phonetic": "きりづま",
      "related_words": {
        "word": [
          "妻",
          "切",
          "切り"
        ]
      },
      "word": "切り妻"
    },
    {
      "_id": "610ad459b1ca11417579d40f7446b4f3",
      "means": [
        {
          "examples": null,
          "kind": "n",
          "mean": "Vợ yêu ."
        }
      ],
      "mobileId": 98501,
      "phonetic": "こいづま",
      "related_words": {
        "word": [
          "恋",
          "妻"
        ]
      },
      "word": "恋妻"
    },
    {
      "_id": "993ac06591dc13e564a87d6ef9bb4b88",
      "means": [
        {
          "examples": [],
          "kind": "n",
          "mean": "tường bên"
        }
      ],
      "mobileId": 278721,
      "phonetic": "つまがべ",
      "word": "妻壁"
    },
    {
      "_id": "c1501ee68b95a76792cb85cf0d128a6d",
      "means": [
        {
          "examples": null,
          "kind": "n",
          "mean": "người đàn ông với vợ và kid(s)"
        }
      ],
      "mobileId": 146334,
      "phonetic": "つまこもち",
      "related_words": {
        "word": [
          "子",
          "妻",
          "妻子"
        ]
      },
      "word": "妻子持ち"
    }
  ],
  "found": true,
  "status": 200
}