{
  "data": [
    {
      "_id": "fe59d178662ff4b87a141c757f4e4520",
      "means": [
        {
          "examples": null,
          "kind": null,
          "mean": "bản ."
        }
      ],
      "mobileId": 186279,
      "phonetic": "ばん",
      "related_words": {
        "word": [
          "掲示板",
          "看板",
          "基板",
          "鋼板",
          "板金",
          "鉄板",
          "黒板",
          "合板",
          "伝言板",
          "鉄板焼き"
        ]
      },
      "synsets": [
        {
          "base_form": "板",
          "entry": [
            {
              "definition_id": "",
              "synonym": [
                "舞台",
                "ステージ"
              ]
            },
            {
              "definition_id": "",
              "synonym": [
                "厚板",
                "ボード",
                "平板"
              ]
            },
            {
              "definition_id": "",
              "synonym": [
                "ボード"
              ]
            }
          ],
          "pos": "noun"
        }
      ],
      "word": "板"
    },
    {
      "_id": "fe59d178662ff4b87a141c757f4e41e1",
      "means": [
        {
          "examples": [
            {
              "content": "板材",
              "mean": "tấm gỗ",
              "transcription": "いたざい"
            },
            {
              "content": "板ガラス",
              "mean": "kính tấm",
              "transcription": "いたがらす"
            }
          ],
          "kind": "n",
          "mean": "tấm ván"
        },
        {
          "examples": null,
          "kind": "n",
          "mean": "ván"
        }
      ],
      "mobileId": 186278,
      "phonetic": "いた",
      "related_words": {
        "word": [
          "掲示板",
          "看板",
          "基板",
          "鋼板",
          "板金",
          "鉄板",
          "黒板",
          "合板",
          "伝言板",
          "鉄板焼き"
        ]
      },
      "synsets": [
        {
          "base_form": "板",
          "entry": [
            {
              "definition_id": "",
              "synonym": [
                "舞台",
                "ステージ"
              ]
            },
            {
              "definition_id": "",
              "synonym": [
                "厚板",
                "ボード",
                "平板"
              ]
            },
            {
              "definition_id": "",
              "synonym": [
                "ボード"
              ]
            }
          ],
          "pos": "noun"
        }
      ],
      "word": "板"
    },
    {
      "_id": "0a951fdb8a16236250ffda52cdb5af3b",
      "means": [
        {
          "examples": null,
          "kind": "n",
          "mean": "tấm (tờ,lá); làm mỏng đĩa"
        }
      ],
      "mobileId": 15551,
      "phonetic": "うすいいた",
      "word": "薄い板"
    },
    {
      "_id": "0a951fdb8a16236250ffda52cdeea27f",
      "means": [
        {
          "examples": null,
          "kind": "n",
          "mean": "tấm chì, miếng chì"
        }
      ],
      "mobileId": 17325,
      "phonetic": "なまりいた",
      "related_words": {
        "word": [
          "板",
          "鉛"
        ]
      },
      "word": "鉛板"
    },
    {
      "_id": "01cb4a7871f6a5fd92ff5dab68f2d9e3",
      "means": [
        {
          "examples": null,
          "kind": "n",
          "mean": "cái chắn bùn, bảng đồng hồ (bảng đặt các đồng hồ đo tốc độ, mức dầu mỡ... ở ô tô)"
        },
        {
          "examples": null,
          "kind": "n",
          "mean": "mảnh vải bịt ngang trán, trán, màn che trước bàn thờ"
        }
      ],
      "mobileId": 7739,
      "phonetic": "ぜんいた",
      "related_words": {
        "word": [
          "前",
          "板"
        ]
      },
      "word": "前板"
    },
    {
      "_id": "0a951fdb8a16236250ffda52cd7399df",
      "means": [
        {
          "examples": null,
          "kind": "n",
          "mean": "rào chắn quanh bằng các tấm ghép; hàng rào bằng các tấm ghép"
        }
      ],
      "mobileId": 13467,
      "phonetic": "いたかこい",
      "word": "板囲い"
    },
    {
      "_id": "2ff8571a77cebf5bd97fd4cca053b01a",
      "means": [
        {
          "examples": null,
          "kind": "n",
          "mean": "clay tablet, clay disc"
        }
      ],
      "mobileId": 283643,
      "phonetic": "ねんどばん",
      "word": "粘土板"
    },
    {
      "_id": "35e94b76fb726c8818e40de107ea20bb",
      "means": [
        {
          "examples": [
            {
              "content": "毒々しい色彩の広告板",
              "mean": "Bảng yết thị (biển quảng cáo, bảng quảng cáo) với màu sắc loè loẹt.",
              "transcription": "どくどくしいしきさいのこうこくばん"
            },
            {
              "content": "通りの広告板",
              "mean": "Bảng yết thị (biển quảng cáo) trên đường phố",
              "transcription": "とおりのこうこくばん"
            },
            {
              "content": "車の広告板",
              "mean": "Bảng yết thị (biển quảng cáo, bảng quảng cáo) trên xe ô tô",
              "transcription": "くるまのこうこくばん"
            },
            {
              "content": "サンドイッチマンが持つ広告板",
              "mean": "Bảng yết thị (biển quảng cáo, bảng quảng cáo) do người bán bánh sandwich mang theo",
              "transcription": "サンドイッチマンがもつこうこくばん"
            },
            {
              "content": "広告板で宣伝する",
              "mean": "Tuyên truyền bằng bảng yết thị (biển quảng cáo) .",
              "transcription": "こうこくばんでせんでんする"
            }
          ],
          "kind": "n",
          "mean": "Bảng yết thị; biển quảng cáo; bảng quảng cáo"
        }
      ],
      "mobileId": 55763,
      "phonetic": "こうこくばん",
      "related_words": {
        "word": [
          "広告",
          "板"
        ]
      },
      "synsets": [
        {
          "base_form": "広告板",
          "entry": [
            {
              "definition_id": "",
              "synonym": [
                "サインボード",
                "看板"
              ]
            }
          ],
          "pos": "noun"
        }
      ],
      "word": "広告板"
    },
    {
      "_id": "2ff8571a77cebf5bd97fd4cca0ad6202",
      "means": [
        {
          "examples": null,
          "kind": "n",
          "mean": "sliced veneer, veneer"
        }
      ],
      "mobileId": 286500,
      "phonetic": "つきいた",
      "word": "突板"
    },
    {
      "_id": "45cb52b868cdf707f15bbf08c09c6857",
      "means": [
        {
          "examples": null,
          "kind": "n",
          "mean": "piece of stiff fabric worn under an obi to give more shape"
        },
        {
          "examples": null,
          "kind": null,
          "mean": "batten plate, stay plate"
        }
      ],
      "mobileId": 211885,
      "phonetic": "おびいた",
      "word": "帯板"
    }
  ],
  "found": true,
  "status": 200
}