{
  "data": [
    {
      "_id": "432518852de0a80625d585a98229a9be",
      "means": [
        {
          "examples": null,
          "kind": "n",
          "mean": "a weight"
        },
        {
          "examples": null,
          "kind": null,
          "mean": "temple supervisor"
        },
        {
          "examples": null,
          "kind": null,
          "mean": "town (of China)"
        }
      ],
      "mobileId": 232951,
      "phonetic": "ちん しず",
      "word": "鎮"
    },
    {
      "_id": "993ac06591dc13e564a87d6ef9bd687a",
      "means": [
        {
          "examples": null,
          "kind": "n",
          "mean": "jiedushi, regional military governor in ancient China"
        }
      ],
      "mobileId": 278791,
      "phonetic": "はんちん",
      "word": "藩鎮"
    },
    {
      "_id": "ebf2f73762939adfacdaeb3c77ba9a7d",
      "means": [
        {
          "examples": null,
          "kind": "n",
          "mean": "Saturn (planet)"
        }
      ],
      "mobileId": 270501,
      "phonetic": "ちんせい",
      "word": "鎮星"
    },
    {
      "_id": "18dd57e50094ff765ae2fa2a3a5631c5",
      "means": [
        {
          "examples": null,
          "kind": "n, vs",
          "mean": "religious ceremony (to appease the gods)"
        }
      ],
      "mobileId": 226166,
      "phonetic": "ちんさい",
      "word": "鎮祭"
    },
    {
      "_id": "ebf2f73762939adfacdaeb3c777d7273",
      "means": [
        {
          "examples": null,
          "kind": "n",
          "mean": "spasmolysis"
        },
        {
          "examples": null,
          "kind": "adj-no",
          "mean": "spasmolytic, antispasmodic, anticonvulsive"
        }
      ],
      "mobileId": 268524,
      "phonetic": "ちんけい",
      "word": "鎮痙"
    },
    {
      "_id": "ebf2f73762939adfacdaeb3c777d65b6",
      "means": [
        {
          "examples": null,
          "kind": "n",
          "mean": "antispasmodic drug, spasmolytic drug, anticonvulsant drug"
        }
      ],
      "mobileId": 268522,
      "phonetic": "ちんけいやく",
      "word": "鎮痙薬"
    },
    {
      "_id": "01cb4a7871f6a5fd92ff5dab689867e0",
      "means": [
        {
          "examples": null,
          "kind": "n",
          "mean": "ba thành phố wuhan"
        }
      ],
      "mobileId": 4833,
      "phonetic": "",
      "word": "武漢三鎮"
    },
    {
      "_id": "e5de112ef7554845e4d6997d6dad7c1c",
      "means": [
        {
          "examples": null,
          "kind": "n",
          "mean": "township and village enterprise in China"
        }
      ],
      "mobileId": 220704,
      "phonetic": "ごうちんきぎょう",
      "word": "郷鎮企業"
    },
    {
      "_id": "2ff8571a77cebf5bd97fd4cca0bbf72d",
      "means": [
        {
          "examples": null,
          "kind": "n",
          "mean": "goods buried during the ground-breaking ceremony for a temple"
        }
      ],
      "mobileId": 286996,
      "phonetic": "ちんだんぐ",
      "word": "鎮壇具"
    }
  ],
  "found": true,
  "status": 200
}