{
  "data": [
    {
      "_id": "432518852de0a80625d585a9825e8275",
      "means": [
        {
          "examples": null,
          "kind": "n",
          "mean": "peng (in Chinese mythology, giant bird said to transform from a fish)"
        }
      ],
      "mobileId": 234620,
      "phonetic": "ほう ぼう",
      "word": "鵬"
    },
    {
      "_id": "45cb52b868cdf707f15bbf08c0a74b70",
      "means": [
        {
          "examples": null,
          "kind": "n",
          "mean": "era during 1960s dominated by grand champions Taiho and Kashiwado"
        }
      ],
      "mobileId": 212213,
      "phonetic": "はくほう",
      "word": "柏鵬"
    },
    {
      "_id": "45cb52b868cdf707f15bbf08c0a78575",
      "means": [
        {
          "examples": null,
          "kind": "n",
          "mean": "era during 1960s dominated by grand champions Taiho and Kashiwado"
        }
      ],
      "mobileId": 212220,
      "phonetic": "はくほうじだい",
      "word": "柏鵬時代"
    }
  ],
  "found": true,
  "status": 200
}